{
  "appPageId" : "796524e9-ffaa-4dde-ae5c-f9d6d6618a64",
  "componentName" : "siteforce:dynamicLayout",
  "dataProviders" : [ ],
  "id" : "76cedb22-cbd5-4e47-82f3-377c380cc5c3",
  "label" : "MDF を表示",
  "regions" : [ {
    "components" : [ {
      "componentAttributes" : {
        "background" : "background: rgba(0,0,0,0)",
        "backgroundOverlay" : "rgba(0,0,0,0.5)",
        "contentAreaWidth" : 100,
        "sectionConfig" : {
          "UUID" : "56d93dce-10f7-425c-8cf0-3765452982f6",
          "columns" : [ {
            "UUID" : "0ccfb561-f731-49c6-bd4d-37e4d8331a2e",
            "columnKey" : "col1",
            "columnName" : "MDF and Coop Column",
            "columnWidth" : "12",
            "seedComponents" : [ {
              "attributes" : {
                "filterName" : "Recent",
                "scope" : "PartnerFundRequest",
                "sfdc:identifier" : "forceCommunity_objectHome"
              },
              "fqn" : "forceCommunity:objectHome"
            } ]
          } ]
        },
        "sectionHeight" : 32
      },
      "componentName" : "forceCommunity:section",
      "id" : "56d93dce-10f7-425c-8cf0-3765452982f6",
      "regions" : [ {
        "components" : [ {
          "componentAttributes" : {
            "enableInlineEdit" : true,
            "filterName" : "Recent",
            "layout" : "FULL",
            "pageSize" : 25,
            "scope" : "PartnerFundRequest",
            "showActionBar" : true,
            "showChartsPanel" : true,
            "showDisplay" : "showall",
            "showFilterPanel" : true,
            "showImageIcon" : true,
            "showManualRefreshButton" : true,
            "showObjectName" : true,
            "showPinnedList" : true,
            "showSearchBar" : true
          },
          "componentName" : "forceCommunity:objectHome",
          "id" : "6d6ed853-3b7e-4960-93eb-06f2e2c59040",
          "renderPriority" : "NEUTRAL",
          "renditionMap" : { },
          "type" : "component"
        } ],
        "id" : "0ccfb561-f731-49c6-bd4d-37e4d8331a2e",
        "regionLabel" : "MDF and Coop Column",
        "regionName" : "col1",
        "renditionMap" : { },
        "type" : "region"
      } ],
      "renderPriority" : "NEUTRAL",
      "renditionMap" : { },
      "type" : "component"
    } ],
    "id" : "79cf3bb8-26fc-4905-becd-2850ea6285d7",
    "regionName" : "content",
    "type" : "region"
  } ],
  "themeLayoutType" : "Inner",
  "type" : "view",
  "viewType" : "mdf"
}